{
    "name": "BLOCK-297",
    "id": "d26887af-27d7-40b3-8ba7-74835a1e6290",
    "program": "ops-rehearsal-4-208",
    "constraints": [],
    "scripts": [
        {
            "name": "run_command.py",
            "standard": true,
            "parameters": {
                "component": "CCCamera",
                "cmd": "play",
                "parameters": {
                    "playlist": "ops-rehearsal-4-208_playlist_60",
                    "repeat": false
                }
            }
        },
        {
            "name": "maintel/take_image_comcam.py",
            "standard": true,
            "parameters": {
                "exp_times": 30.0,
                "note": "Rubin_SV_280_-48 208 01/60",
                "filter": "r_03",
                "slew_time": 154.79654657530278,
                "image_type": "OBJECT",
                "nimages": 1,
                "program": "BLOCK-297",
                "sim": true,
                "visit_metadata": {
                    "ra": 18.6469927906798,
                    "dec": -48.01175241141816,
                    "rot_sky": -116.76080168456154
                }
            }
        },
        {
            "name": "maintel/take_image_comcam.py",
            "standard": true,
            "parameters": {
                "exp_times": 30.0,
                "note": "Rubin_SV_280_-48 208 02/60",
                "filter": "r_03",
                "slew_time": 3.183271639676974,
                "image_type": "OBJECT",
                "nimages": 1,
                "program": "BLOCK-297",
                "sim": true,
                "visit_metadata": {
                    "ra": 18.649331685420524,
                    "dec": -48.03102036952514,
                    "rot_sky": -117.5005507587123
                }
            }
        },
        {
            "name": "maintel/take_image_comcam.py",
            "standard": true,
            "parameters": {
                "exp_times": 30.0,
                "note": "Rubin_SV_280_-48 208 03/60",
                "filter": "r_03",
                "slew_time": 3.6646504352661062,
                "image_type": "OBJECT",
                "nimages": 1,
                "program": "BLOCK-297",
                "sim": true,
                "visit_metadata": {
                    "ra": 18.673894073227466,
                    "dec": -47.904728955861806,
                    "rot_sky": -119.178871326201
                }
            }
        },
        {
            "name": "maintel/take_image_comcam.py",
            "standard": true,
            "parameters": {
                "exp_times": 30.0,
                "note": "Rubin_SV_280_-48 208 04/60",
                "filter": "r_03",
                "slew_time": 3.6991214940217114,
                "image_type": "OBJECT",
                "nimages": 1,
                "program": "BLOCK-297",
                "sim": true,
                "visit_metadata": {
                    "ra": 18.65250881825357,
                    "dec": -48.12422599594058,
                    "rot_sky": -118.83604088806005
                }
            }
        },
        {
            "name": "maintel/take_image_comcam.py",
            "standard": true,
            "parameters": {
                "exp_times": 30.0,
                "note": "Rubin_SV_280_-48 208 05/60",
                "filter": "r_03",
                "slew_time": 3.6439429079060037,
                "image_type": "OBJECT",
                "nimages": 1,
                "program": "BLOCK-297",
                "sim": true,
                "visit_metadata": {
                    "ra": 18.682522083450355,
                    "dec": -48.102054055795755,
                    "rot_sky": -120.52604728050933
                }
            }
        },
        {
            "name": "maintel/take_image_comcam.py",
            "standard": true,
            "parameters": {
                "exp_times": 30.0,
                "note": "Rubin_SV_280_-48 208 06/60",
                "filter": "r_03",
                "slew_time": 3.404310267321819,
                "image_type": "OBJECT",
                "nimages": 1,
                "program": "BLOCK-297",
                "sim": true,
                "visit_metadata": {
                    "ra": 18.685404176139492,
                    "dec": -47.969371474934064,
                    "rot_sky": -121.51975426593881
                }
            }
        },
        {
            "name": "maintel/take_image_comcam.py",
            "standard": true,
            "parameters": {
                "exp_times": 30.0,
                "note": "Rubin_SV_280_-48 208 07/60",
                "filter": "r_03",
                "slew_time": 3.4797273503025137,
                "image_type": "OBJECT",
                "nimages": 1,
                "program": "BLOCK-297",
                "sim": true,
                "visit_metadata": {
                    "ra": 18.666411735003432,
                    "dec": -47.85835424829709,
                    "rot_sky": -121.7663219420609
                }
            }
        },
        {
            "name": "maintel/take_image_comcam.py",
            "standard": true,
            "parameters": {
                "exp_times": 30.0,
                "note": "Rubin_SV_280_-48 208 08/60",
                "filter": "r_03",
                "slew_time": 3.310325194552683,
                "image_type": "OBJECT",
                "nimages": 1,
                "program": "BLOCK-297",
                "sim": true,
                "visit_metadata": {
                    "ra": 18.65808836548364,
                    "dec": -47.84068396601334,
                    "rot_sky": -122.20644294798404
                }
            }
        },
        {
            "name": "maintel/take_image_comcam.py",
            "standard": true,
            "parameters": {
                "exp_times": 30.0,
                "note": "Rubin_SV_280_-48 208 09/60",
                "filter": "r_03",
                "slew_time": 3.4379503419947617,
                "image_type": "OBJECT",
                "nimages": 1,
                "program": "BLOCK-297",
                "sim": true,
                "visit_metadata": {
                    "ra": 18.66294857882984,
                    "dec": -48.01063456884663,
                    "rot_sky": -122.78787874770899
                }
            }
        },
        {
            "name": "maintel/take_image_comcam.py",
            "standard": true,
            "parameters": {
                "exp_times": 30.0,
                "note": "Rubin_SV_280_-48 208 10/60",
                "filter": "r_03",
                "slew_time": 3.2936147675604874,
                "image_type": "OBJECT",
                "nimages": 1,
                "program": "BLOCK-297",
                "sim": true,
                "visit_metadata": {
                    "ra": 18.66617004442129,
                    "dec": -48.07984253249626,
                    "rot_sky": -123.47373191066474
                }
            }
        },
        {
            "name": "maintel/take_image_comcam.py",
            "standard": true,
            "parameters": {
                "exp_times": 30.0,
                "note": "Rubin_SV_280_-48 208 11/60",
                "filter": "r_03",
                "slew_time": 3.3978584667689966,
                "image_type": "OBJECT",
                "nimages": 1,
                "program": "BLOCK-297",
                "sim": true,
                "visit_metadata": {
                    "ra": 18.65823713833278,
                    "dec": -48.13475489128129,
                    "rot_sky": -123.81095230343941
                }
            }
        },
        {
            "name": "maintel/take_image_comcam.py",
            "standard": true,
            "parameters": {
                "exp_times": 30.0,
                "note": "Rubin_SV_280_-48 208 12/60",
                "filter": "r_03",
                "slew_time": 3.4070182324198157,
                "image_type": "OBJECT",
                "nimages": 1,
                "program": "BLOCK-297",
                "sim": true,
                "visit_metadata": {
                    "ra": 18.660426010912033,
                    "dec": -47.98463722559977,
                    "rot_sky": -124.79074168151641
                }
            }
        },
        {
            "name": "maintel/take_image_comcam.py",
            "standard": true,
            "parameters": {
                "exp_times": 30.0,
                "note": "Rubin_SV_280_-48 208 13/60",
                "filter": "r_03",
                "slew_time": 3.345295152489668,
                "image_type": "OBJECT",
                "nimages": 1,
                "program": "BLOCK-297",
                "sim": true,
                "visit_metadata": {
                    "ra": 18.67068498683678,
                    "dec": -48.01034515849938,
                    "rot_sky": -125.77554685446668
                }
            }
        },
        {
            "name": "maintel/take_image_comcam.py",
            "standard": true,
            "parameters": {
                "exp_times": 30.0,
                "note": "Rubin_SV_280_-48 208 14/60",
                "filter": "r_03",
                "slew_time": 3.332010671848126,
                "image_type": "OBJECT",
                "nimages": 1,
                "program": "BLOCK-297",
                "sim": true,
                "visit_metadata": {
                    "ra": 18.663091466043632,
                    "dec": -47.944809728007655,
                    "rot_sky": -126.29799422756153
                }
            }
        },
        {
            "name": "maintel/take_image_comcam.py",
            "standard": true,
            "parameters": {
                "exp_times": 30.0,
                "note": "Rubin_SV_280_-48 208 15/60",
                "filter": "r_03",
                "slew_time": 3.4688429505468594,
                "image_type": "OBJECT",
                "nimages": 1,
                "program": "BLOCK-297",
                "sim": true,
                "visit_metadata": {
                    "ra": 18.669525075508183,
                    "dec": -48.13174110653816,
                    "rot_sky": -126.9131224011384
                }
            }
        },
        {
            "name": "maintel/take_image_comcam.py",
            "standard": true,
            "parameters": {
                "exp_times": 30.0,
                "note": "Rubin_SV_280_-48 208 16/60",
                "filter": "r_03",
                "slew_time": 3.2382168433211316,
                "image_type": "OBJECT",
                "nimages": 1,
                "program": "BLOCK-297",
                "sim": true,
                "visit_metadata": {
                    "ra": 18.673089820736944,
                    "dec": -48.12404092683475,
                    "rot_sky": -127.72359928821214
                }
            }
        },
        {
            "name": "maintel/take_image_comcam.py",
            "standard": true,
            "parameters": {
                "exp_times": 30.0,
                "note": "Rubin_SV_280_-48 208 17/60",
                "filter": "r_03",
                "slew_time": 3.581886891608655,
                "image_type": "OBJECT",
                "nimages": 1,
                "program": "BLOCK-297",
                "sim": true,
                "visit_metadata": {
                    "ra": 18.68207800450549,
                    "dec": -47.88571867887581,
                    "rot_sky": -129.0566849832494
                }
            }
        },
        {
            "name": "maintel/take_image_comcam.py",
            "standard": true,
            "parameters": {
                "exp_times": 30.0,
                "note": "Rubin_SV_280_-48 208 18/60",
                "filter": "r_03",
                "slew_time": 3.3351742048105653,
                "image_type": "OBJECT",
                "nimages": 1,
                "program": "BLOCK-297",
                "sim": true,
                "visit_metadata": {
                    "ra": 18.67911210906721,
                    "dec": -47.96454221553831,
                    "rot_sky": -129.5129597986118
                }
            }
        },
        {
            "name": "maintel/take_image_comcam.py",
            "standard": true,
            "parameters": {
                "exp_times": 30.0,
                "note": "Rubin_SV_280_-48 208 19/60",
                "filter": "r_03",
                "slew_time": 3.2388966745511536,
                "image_type": "OBJECT",
                "nimages": 1,
                "program": "BLOCK-297",
                "sim": true,
                "visit_metadata": {
                    "ra": 18.68090867391422,
                    "dec": -48.01209930256263,
                    "rot_sky": -130.17897381067291
                }
            }
        },
        {
            "name": "maintel/take_image_comcam.py",
            "standard": true,
            "parameters": {
                "exp_times": 30.0,
                "note": "Rubin_SV_280_-48 208 20/60",
                "filter": "r_03",
                "slew_time": 3.5483622147574314,
                "image_type": "OBJECT",
                "nimages": 1,
                "program": "BLOCK-297",
                "sim": true,
                "visit_metadata": {
                    "ra": 18.655356533693514,
                    "dec": -47.85954795716978,
                    "rot_sky": -130.18733964777522
                }
            }
        },
        {
            "name": "maintel/take_image_comcam.py",
            "standard": true,
            "parameters": {
                "exp_times": 30.0,
                "note": "Rubin_SV_280_-48 208 21/60",
                "filter": "g_01",
                "slew_time": 120.0,
                "image_type": "OBJECT",
                "nimages": 1,
                "program": "BLOCK-297",
                "sim": true,
                "visit_metadata": {
                    "ra": 18.657812561118707,
                    "dec": -48.15720917017828,
                    "rot_sky": -118.05899189855513
                }
            }
        },
        {
            "name": "maintel/take_image_comcam.py",
            "standard": true,
            "parameters": {
                "exp_times": 30.0,
                "note": "Rubin_SV_280_-48 208 22/60",
                "filter": "g_01",
                "slew_time": 3.666942795390847,
                "image_type": "OBJECT",
                "nimages": 1,
                "program": "BLOCK-297",
                "sim": true,
                "visit_metadata": {
                    "ra": 18.677857605951715,
                    "dec": -47.978988387631986,
                    "rot_sky": -119.67284544487156
                }
            }
        },
        {
            "name": "maintel/take_image_comcam.py",
            "standard": true,
            "parameters": {
                "exp_times": 30.0,
                "note": "Rubin_SV_280_-48 208 23/60",
                "filter": "g_01",
                "slew_time": 3.5486080651409844,
                "image_type": "OBJECT",
                "nimages": 1,
                "program": "BLOCK-297",
                "sim": true,
                "visit_metadata": {
                    "ra": 18.66814508793015,
                    "dec": -48.169597302595335,
                    "rot_sky": -119.72758052854753
                }
            }
        },
        {
            "name": "maintel/take_image_comcam.py",
            "standard": true,
            "parameters": {
                "exp_times": 30.0,
                "note": "Rubin_SV_280_-48 208 24/60",
                "filter": "g_01",
                "slew_time": 3.6257003414639337,
                "image_type": "OBJECT",
                "nimages": 1,
                "program": "BLOCK-297",
                "sim": true,
                "visit_metadata": {
                    "ra": 18.655471486824364,
                    "dec": -47.84909806467,
                    "rot_sky": -120.37105589189719
                }
            }
        },
        {
            "name": "maintel/take_image_comcam.py",
            "standard": true,
            "parameters": {
                "exp_times": 30.0,
                "note": "Rubin_SV_280_-48 208 25/60",
                "filter": "g_01",
                "slew_time": 3.511258545886458,
                "image_type": "OBJECT",
                "nimages": 1,
                "program": "BLOCK-297",
                "sim": true,
                "visit_metadata": {
                    "ra": 18.650866772982486,
                    "dec": -48.08848822611234,
                    "rot_sky": -120.53614297025948
                }
            }
        },
        {
            "name": "maintel/take_image_comcam.py",
            "standard": true,
            "parameters": {
                "exp_times": 30.0,
                "note": "Rubin_SV_280_-48 208 26/60",
                "filter": "g_01",
                "slew_time": 3.7105920828618237,
                "image_type": "OBJECT",
                "nimages": 1,
                "program": "BLOCK-297",
                "sim": true,
                "visit_metadata": {
                    "ra": 18.677561831867532,
                    "dec": -47.96582788641387,
                    "rot_sky": -122.31281885518655
                }
            }
        },
        {
            "name": "maintel/take_image_comcam.py",
            "standard": true,
            "parameters": {
                "exp_times": 30.0,
                "note": "Rubin_SV_280_-48 208 27/60",
                "filter": "g_01",
                "slew_time": 3.3108534786778505,
                "image_type": "OBJECT",
                "nimages": 1,
                "program": "BLOCK-297",
                "sim": true,
                "visit_metadata": {
                    "ra": 18.679989691101216,
                    "dec": -47.891924972703436,
                    "rot_sky": -123.15799370346028
                }
            }
        },
        {
            "name": "maintel/take_image_comcam.py",
            "standard": true,
            "parameters": {
                "exp_times": 30.0,
                "note": "Rubin_SV_280_-48 208 28/60",
                "filter": "g_01",
                "slew_time": 3.5425665122044236,
                "image_type": "OBJECT",
                "nimages": 1,
                "program": "BLOCK-297",
                "sim": true,
                "visit_metadata": {
                    "ra": 18.674277472684672,
                    "dec": -48.15392451008787,
                    "rot_sky": -123.25542896891545
                }
            }
        },
        {
            "name": "maintel/take_image_comcam.py",
            "standard": true,
            "parameters": {
                "exp_times": 30.0,
                "note": "Rubin_SV_280_-48 208 29/60",
                "filter": "g_01",
                "slew_time": 3.4582655245121434,
                "image_type": "OBJECT",
                "nimages": 1,
                "program": "BLOCK-297",
                "sim": true,
                "visit_metadata": {
                    "ra": 18.657419989415676,
                    "dec": -48.03275724890425,
                    "rot_sky": -123.45608500953779
                }
            }
        },
        {
            "name": "maintel/take_image_comcam.py",
            "standard": true,
            "parameters": {
                "exp_times": 30.0,
                "note": "Rubin_SV_280_-48 208 30/60",
                "filter": "g_01",
                "slew_time": 3.438581660491247,
                "image_type": "OBJECT",
                "nimages": 1,
                "program": "BLOCK-297",
                "sim": true,
                "visit_metadata": {
                    "ra": 18.669426878595175,
                    "dec": -48.161320851442,
                    "rot_sky": -124.37837308839482
                }
            }
        },
        {
            "name": "maintel/take_image_comcam.py",
            "standard": true,
            "parameters": {
                "exp_times": 30.0,
                "note": "Rubin_SV_280_-48 208 31/60",
                "filter": "g_01",
                "slew_time": 3.464408878249071,
                "image_type": "OBJECT",
                "nimages": 1,
                "program": "BLOCK-297",
                "sim": true,
                "visit_metadata": {
                    "ra": 18.669788939565006,
                    "dec": -47.949663135807256,
                    "rot_sky": -125.31503856678474
                }
            }
        },
        {
            "name": "maintel/take_image_comcam.py",
            "standard": true,
            "parameters": {
                "exp_times": 30.0,
                "note": "Rubin_SV_280_-48 208 32/60",
                "filter": "g_01",
                "slew_time": 3.3081505426845372,
                "image_type": "OBJECT",
                "nimages": 1,
                "program": "BLOCK-297",
                "sim": true,
                "visit_metadata": {
                    "ra": 18.661777271957966,
                    "dec": -47.90751611626076,
                    "rot_sky": -125.72239173526745
                }
            }
        },
        {
            "name": "maintel/take_image_comcam.py",
            "standard": true,
            "parameters": {
                "exp_times": 30.0,
                "note": "Rubin_SV_280_-48 208 33/60",
                "filter": "g_01",
                "slew_time": 3.396591860124216,
                "image_type": "OBJECT",
                "nimages": 1,
                "program": "BLOCK-297",
                "sim": true,
                "visit_metadata": {
                    "ra": 18.668659079243657,
                    "dec": -48.02709471757696,
                    "rot_sky": -126.47101778188443
                }
            }
        },
        {
            "name": "maintel/take_image_comcam.py",
            "standard": true,
            "parameters": {
                "exp_times": 30.0,
                "note": "Rubin_SV_280_-48 208 34/60",
                "filter": "g_01",
                "slew_time": 3.3707410869907046,
                "image_type": "OBJECT",
                "nimages": 1,
                "program": "BLOCK-297",
                "sim": true,
                "visit_metadata": {
                    "ra": 18.66047835535381,
                    "dec": -48.03717504573635,
                    "rot_sky": -126.80169557685281
                }
            }
        },
        {
            "name": "maintel/take_image_comcam.py",
            "standard": true,
            "parameters": {
                "exp_times": 30.0,
                "note": "Rubin_SV_280_-48 208 35/60",
                "filter": "g_01",
                "slew_time": 3.186712634156416,
                "image_type": "OBJECT",
                "nimages": 1,
                "program": "BLOCK-297",
                "sim": true,
                "visit_metadata": {
                    "ra": 18.66349818325016,
                    "dec": -48.056987657265495,
                    "rot_sky": -127.53599251102163
                }
            }
        },
        {
            "name": "maintel/take_image_comcam.py",
            "standard": true,
            "parameters": {
                "exp_times": 30.0,
                "note": "Rubin_SV_280_-48 208 36/60",
                "filter": "g_01",
                "slew_time": 3.5583618960982646,
                "image_type": "OBJECT",
                "nimages": 1,
                "program": "BLOCK-297",
                "sim": true,
                "visit_metadata": {
                    "ra": 18.67188721200624,
                    "dec": -47.8126098774061,
                    "rot_sky": -128.79301736137853
                }
            }
        },
        {
            "name": "maintel/take_image_comcam.py",
            "standard": true,
            "parameters": {
                "exp_times": 30.0,
                "note": "Rubin_SV_280_-48 208 37/60",
                "filter": "g_01",
                "slew_time": 3.6008465491205497,
                "image_type": "OBJECT",
                "nimages": 1,
                "program": "BLOCK-297",
                "sim": true,
                "visit_metadata": {
                    "ra": 18.65908817698636,
                    "dec": -48.027755235813274,
                    "rot_sky": -128.68702857827753
                }
            }
        },
        {
            "name": "maintel/take_image_comcam.py",
            "standard": true,
            "parameters": {
                "exp_times": 30.0,
                "note": "Rubin_SV_280_-48 208 38/60",
                "filter": "g_01",
                "slew_time": 3.3102678705175577,
                "image_type": "OBJECT",
                "nimages": 1,
                "program": "BLOCK-297",
                "sim": true,
                "visit_metadata": {
                    "ra": 18.666128302141676,
                    "dec": -48.05359057146044,
                    "rot_sky": -129.56200699531738
                }
            }
        },
        {
            "name": "maintel/take_image_comcam.py",
            "standard": true,
            "parameters": {
                "exp_times": 30.0,
                "note": "Rubin_SV_280_-48 208 39/60",
                "filter": "g_01",
                "slew_time": 3.532943248560268,
                "image_type": "OBJECT",
                "nimages": 1,
                "program": "BLOCK-297",
                "sim": true,
                "visit_metadata": {
                    "ra": 18.6746951694923,
                    "dec": -47.84671119342682,
                    "rot_sky": -130.77099642157322
                }
            }
        },
        {
            "name": "maintel/take_image_comcam.py",
            "standard": true,
            "parameters": {
                "exp_times": 30.0,
                "note": "Rubin_SV_280_-48 208 40/60",
                "filter": "g_01",
                "slew_time": 3.4616284794136165,
                "image_type": "OBJECT",
                "nimages": 1,
                "program": "BLOCK-297",
                "sim": true,
                "visit_metadata": {
                    "ra": 18.661782101074312,
                    "dec": -47.846605988256066,
                    "rot_sky": -130.91483555904355
                }
            }
        },
        {
            "name": "maintel/take_image_comcam.py",
            "standard": true,
            "parameters": {
                "exp_times": 30.0,
                "note": "Rubin_SV_280_-48 208 41/60",
                "filter": "i_06",
                "slew_time": 120.0,
                "image_type": "OBJECT",
                "nimages": 1,
                "program": "BLOCK-297",
                "sim": true,
                "visit_metadata": {
                    "ra": 18.682531322430847,
                    "dec": -47.990842580968696,
                    "rot_sky": -72.65985980505457
                }
            }
        },
        {
            "name": "maintel/take_image_comcam.py",
            "standard": true,
            "parameters": {
                "exp_times": 30.0,
                "note": "Rubin_SV_280_-48 208 42/60",
                "filter": "i_06",
                "slew_time": 3.2570864815053695,
                "image_type": "OBJECT",
                "nimages": 1,
                "program": "BLOCK-297",
                "sim": true,
                "visit_metadata": {
                    "ra": 18.684992444094448,
                    "dec": -48.043285141166464,
                    "rot_sky": -73.33024620816379
                }
            }
        },
        {
            "name": "maintel/take_image_comcam.py",
            "standard": true,
            "parameters": {
                "exp_times": 30.0,
                "note": "Rubin_SV_280_-48 208 43/60",
                "filter": "i_06",
                "slew_time": 3.3538846878608335,
                "image_type": "OBJECT",
                "nimages": 1,
                "program": "BLOCK-297",
                "sim": true,
                "visit_metadata": {
                    "ra": 18.67959560738189,
                    "dec": -48.099252032607374,
                    "rot_sky": -73.69509859649537
                }
            }
        },
        {
            "name": "maintel/take_image_comcam.py",
            "standard": true,
            "parameters": {
                "exp_times": 30.0,
                "note": "Rubin_SV_280_-48 208 44/60",
                "filter": "i_06",
                "slew_time": 3.4467746949412312,
                "image_type": "OBJECT",
                "nimages": 1,
                "program": "BLOCK-297",
                "sim": true,
                "visit_metadata": {
                    "ra": 18.6802748056212,
                    "dec": -47.91031667684404,
                    "rot_sky": -74.55613858499646
                }
            }
        },
        {
            "name": "maintel/take_image_comcam.py",
            "standard": true,
            "parameters": {
                "exp_times": 30.0,
                "note": "Rubin_SV_280_-48 208 45/60",
                "filter": "i_06",
                "slew_time": 3.493553440482478,
                "image_type": "OBJECT",
                "nimages": 1,
                "program": "BLOCK-297",
                "sim": true,
                "visit_metadata": {
                    "ra": 18.673338313653275,
                    "dec": -48.1174914448194,
                    "rot_sky": -74.69456807195274
                }
            }
        },
        {
            "name": "maintel/take_image_comcam.py",
            "standard": true,
            "parameters": {
                "exp_times": 30.0,
                "note": "Rubin_SV_280_-48 208 46/60",
                "filter": "i_06",
                "slew_time": 3.5603179381558054,
                "image_type": "OBJECT",
                "nimages": 1,
                "program": "BLOCK-297",
                "sim": true,
                "visit_metadata": {
                    "ra": 18.65229003328783,
                    "dec": -48.04269234767384,
                    "rot_sky": -74.5757442666669
                }
            }
        },
        {
            "name": "maintel/take_image_comcam.py",
            "standard": true,
            "parameters": {
                "exp_times": 30.0,
                "note": "Rubin_SV_280_-48 208 47/60",
                "filter": "i_06",
                "slew_time": 3.7334593330304133,
                "image_type": "OBJECT",
                "nimages": 1,
                "program": "BLOCK-297",
                "sim": true,
                "visit_metadata": {
                    "ra": 18.683687031519312,
                    "dec": -48.03841687138799,
                    "rot_sky": -76.42941282254606
                }
            }
        },
        {
            "name": "maintel/take_image_comcam.py",
            "standard": true,
            "parameters": {
                "exp_times": 30.0,
                "note": "Rubin_SV_280_-48 208 48/60",
                "filter": "i_06",
                "slew_time": 3.691307307847673,
                "image_type": "OBJECT",
                "nimages": 1,
                "program": "BLOCK-297",
                "sim": true,
                "visit_metadata": {
                    "ra": 18.654745140551476,
                    "dec": -48.00699603807453,
                    "rot_sky": -75.9469902774656
                }
            }
        },
        {
            "name": "maintel/take_image_comcam.py",
            "standard": true,
            "parameters": {
                "exp_times": 30.0,
                "note": "Rubin_SV_280_-48 208 49/60",
                "filter": "i_06",
                "slew_time": 3.4978281561077447,
                "image_type": "OBJECT",
                "nimages": 1,
                "program": "BLOCK-297",
                "sim": true,
                "visit_metadata": {
                    "ra": 18.667681251322243,
                    "dec": -47.96341533335234,
                    "rot_sky": -77.12116427883001
                }
            }
        },
        {
            "name": "maintel/take_image_comcam.py",
            "standard": true,
            "parameters": {
                "exp_times": 30.0,
                "note": "Rubin_SV_280_-48 208 50/60",
                "filter": "i_06",
                "slew_time": 3.419618701802638,
                "image_type": "OBJECT",
                "nimages": 1,
                "program": "BLOCK-297",
                "sim": true,
                "visit_metadata": {
                    "ra": 18.67473878285082,
                    "dec": -48.102505674672294,
                    "rot_sky": -77.88671059986063
                }
            }
        },
        {
            "name": "maintel/take_image_comcam.py",
            "standard": true,
            "parameters": {
                "exp_times": 30.0,
                "note": "Rubin_SV_280_-48 208 51/60",
                "filter": "i_06",
                "slew_time": 3.2942489238415296,
                "image_type": "OBJECT",
                "nimages": 1,
                "program": "BLOCK-297",
                "sim": true,
                "visit_metadata": {
                    "ra": 18.677995058890804,
                    "dec": -48.04646658859102,
                    "rot_sky": -78.69264325931829
                }
            }
        },
        {
            "name": "maintel/take_image_comcam.py",
            "standard": true,
            "parameters": {
                "exp_times": 30.0,
                "note": "Rubin_SV_280_-48 208 52/60",
                "filter": "i_06",
                "slew_time": 3.5709582455389954,
                "image_type": "OBJECT",
                "nimages": 1,
                "program": "BLOCK-297",
                "sim": true,
                "visit_metadata": {
                    "ra": 18.65832585470965,
                    "dec": -48.01626327683202,
                    "rot_sky": -78.55836527333452
                }
            }
        },
        {
            "name": "maintel/take_image_comcam.py",
            "standard": true,
            "parameters": {
                "exp_times": 30.0,
                "note": "Rubin_SV_280_-48 208 53/60",
                "filter": "i_06",
                "slew_time": 3.370682268548988,
                "image_type": "OBJECT",
                "nimages": 1,
                "program": "BLOCK-297",
                "sim": true,
                "visit_metadata": {
                    "ra": 18.65265882377899,
                    "dec": -47.90754336941799,
                    "rot_sky": -79.04549949564438
                }
            }
        },
        {
            "name": "maintel/take_image_comcam.py",
            "standard": true,
            "parameters": {
                "exp_times": 30.0,
                "note": "Rubin_SV_280_-48 208 54/60",
                "filter": "i_06",
                "slew_time": 3.5908177795944063,
                "image_type": "OBJECT",
                "nimages": 1,
                "program": "BLOCK-297",
                "sim": true,
                "visit_metadata": {
                    "ra": 18.669483133628194,
                    "dec": -48.177152989882764,
                    "rot_sky": -80.09517290863143
                }
            }
        },
        {
            "name": "maintel/take_image_comcam.py",
            "standard": true,
            "parameters": {
                "exp_times": 30.0,
                "note": "Rubin_SV_280_-48 208 55/60",
                "filter": "i_06",
                "slew_time": 3.4757803231045257,
                "image_type": "OBJECT",
                "nimages": 1,
                "program": "BLOCK-297",
                "sim": true,
                "visit_metadata": {
                    "ra": 18.67351215571633,
                    "dec": -47.95977610707599,
                    "rot_sky": -81.06455044634026
                }
            }
        },
        {
            "name": "maintel/take_image_comcam.py",
            "standard": true,
            "parameters": {
                "exp_times": 30.0,
                "note": "Rubin_SV_280_-48 208 56/60",
                "filter": "i_06",
                "slew_time": 3.4173088110484606,
                "image_type": "OBJECT",
                "nimages": 1,
                "program": "BLOCK-297",
                "sim": true,
                "visit_metadata": {
                    "ra": 18.674287433108553,
                    "dec": -48.11580570678598,
                    "rot_sky": -81.57604726305738
                }
            }
        },
        {
            "name": "maintel/take_image_comcam.py",
            "standard": true,
            "parameters": {
                "exp_times": 30.0,
                "note": "Rubin_SV_280_-48 208 57/60",
                "filter": "i_06",
                "slew_time": 3.1790651608260525,
                "image_type": "OBJECT",
                "nimages": 1,
                "program": "BLOCK-297",
                "sim": true,
                "visit_metadata": {
                    "ra": 18.67397720517746,
                    "dec": -48.0875796319397,
                    "rot_sky": -82.20671305942659
                }
            }
        },
        {
            "name": "maintel/take_image_comcam.py",
            "standard": true,
            "parameters": {
                "exp_times": 30.0,
                "note": "Rubin_SV_280_-48 208 58/60",
                "filter": "i_06",
                "slew_time": 3.5387067398922114,
                "image_type": "OBJECT",
                "nimages": 1,
                "program": "BLOCK-297",
                "sim": true,
                "visit_metadata": {
                    "ra": 18.662414385952196,
                    "dec": -47.85545938769101,
                    "rot_sky": -82.5429022171719
                }
            }
        },
        {
            "name": "maintel/take_image_comcam.py",
            "standard": true,
            "parameters": {
                "exp_times": 30.0,
                "note": "Rubin_SV_280_-48 208 59/60",
                "filter": "i_06",
                "slew_time": 3.429543335592782,
                "image_type": "OBJECT",
                "nimages": 1,
                "program": "BLOCK-297",
                "sim": true,
                "visit_metadata": {
                    "ra": 18.67275829790712,
                    "dec": -47.99561837885371,
                    "rot_sky": -83.45962115486702
                }
            }
        },
        {
            "name": "maintel/take_image_comcam.py",
            "standard": true,
            "parameters": {
                "exp_times": 30.0,
                "note": "Rubin_SV_280_-48 208 60/60",
                "filter": "i_06",
                "slew_time": 3.4873282069591136,
                "image_type": "OBJECT",
                "nimages": 1,
                "program": "BLOCK-297",
                "sim": true,
                "visit_metadata": {
                    "ra": 18.685884304040247,
                    "dec": -47.98772904003017,
                    "rot_sky": -84.60873536229474
                }
            }
        }
    ]
}